{
  "globals": {
    "$t": true,
    "Component": true,
    "ComponentPublicInstance": true,
    "ComputedRef": true,
    "Debounce": true,
    "DirectiveBinding": true,
    "EMAIL_REGEXP": true,
    "EffectScope": true,
    "ElMessage": true,
    "ElMessageBox": true,
    "ExtractDefaultPropTypes": true,
    "ExtractPropTypes": true,
    "ExtractPublicPropTypes": true,
    "InjectionKey": true,
    "MOBILE_REGEXP": true,
    "MaybeRef": true,
    "MaybeRefOrGetter": true,
    "PASSWORD_REGEXP": true,
    "PropType": true,
    "Ref": true,
    "ShallowRef": true,
    "Slot": true,
    "Slots": true,
    "UNIFIED_SOCIAL_CREDIT_CODE": true,
    "USER_NAME_REGEXP": true,
    "VNode": true,
    "WritableComputedRef": true,
    "addClass": true,
    "areaNameList": true,
    "bigNumberTransform": true,
    "byteLength": true,
    "checkIDCard": true,
    "cleanArray": true,
    "computed": true,
    "configDefInfo": true,
    "createApp": true,
    "createUniqueString": true,
    "customRef": true,
    "debounce": true,
    "deepClone": true,
    "defineAsyncComponent": true,
    "defineComponent": true,
    "effectScope": true,
    "excelRequest": true,
    "flatten": true,
    "formatConfigInfo": true,
    "formatHtml": true,
    "formatPrice": true,
    "formatTime": true,
    "generateTitle": true,
    "getCurrentInstance": true,
    "getCurrentScope": true,
    "getCurrentWatcher": true,
    "getDateTimeRange": true,
    "getLevels": true,
    "getParseTime": true,
    "getQueryObject": true,
    "getTime": true,
    "getToken": true,
    "getUUID": true,
    "h": true,
    "handleArr": true,
    "hasClass": true,
    "html2Text": true,
    "idList": true,
    "inject": true,
    "isArray": true,
    "isCreditCode": true,
    "isEmail": true,
    "isExternal": true,
    "isHtmlNull": true,
    "isMatching": true,
    "isMobile": true,
    "isProxy": true,
    "isReactive": true,
    "isReadonly": true,
    "isRef": true,
    "isShallow": true,
    "isString": true,
    "isUserName": true,
    "markRaw": true,
    "nextTick": true,
    "noSpacesBothSides": true,
    "objectMerge": true,
    "onActivated": true,
    "onBeforeMount": true,
    "onBeforeRouteLeave": true,
    "onBeforeRouteUpdate": true,
    "onBeforeUnmount": true,
    "onBeforeUpdate": true,
    "onDeactivated": true,
    "onErrorCaptured": true,
    "onMounted": true,
    "onRenderTracked": true,
    "onRenderTriggered": true,
    "onScopeDispose": true,
    "onServerPrefetch": true,
    "onUnmounted": true,
    "onUpdated": true,
    "onWatcherCleanup": true,
    "param": true,
    "param2Obj": true,
    "parseTime": true,
    "provide": true,
    "reactive": true,
    "readonly": true,
    "ref": true,
    "removeClass": true,
    "removeToken": true,
    "request": true,
    "resolveComponent": true,
    "setToken": true,
    "setupStore": true,
    "shallowReactive": true,
    "shallowReadonly": true,
    "shallowRef": true,
    "store": true,
    "toRaw": true,
    "toRef": true,
    "toRefs": true,
    "toValue": true,
    "toggleClass": true,
    "treeDataTranslate": true,
    "triggerRef": true,
    "uniqueArr": true,
    "unref": true,
    "useAppStore": true,
    "useAttrs": true,
    "useCancelFocusIntervalStore": true,
    "useCommonStore": true,
    "useCssModule": true,
    "useCssVars": true,
    "useId": true,
    "useLink": true,
    "useModel": true,
    "usePermissionStore": true,
    "useRoute": true,
    "useRouter": true,
    "useSlots": true,
    "useTemplateRef": true,
    "useUserStore": true,
    "useWebConfigStore": true,
    "validAlphabets": true,
    "validEmail": true,
    "validLowerCase": true,
    "validNoEmptySpace": true,
    "validPassword": true,
    "validURL": true,
    "validUpperCase": true,
    "validUsername": true,
    "watch": true,
    "watchEffect": true,
    "watchPostEffect": true,
    "watchSyncEffect": true
  }
}
